beekeeper/readers/watson_discovery/__init__.py
beekeeper/readers/watson_discovery/base.py
beekeeper_readers_watson_discovery-1.0.0.dist-info/METADATA
beekeeper_readers_watson_discovery-1.0.0.dist-info/WHEEL
beekeeper_readers_watson_discovery-1.0.0.dist-info/RECORD
